outfit/__init__.py
outfit/models.py
outfit/utils.py
outfit/wardrobe.py
outfit-0.0.2.dist-info/METADATA
outfit-0.0.2.dist-info/WHEEL
outfit-0.0.2.dist-info/top_level.txt
outfit-0.0.2.dist-info/RECORD
