Metadata-Version: 2.1
Name: outfit
Version: 0.0.2
Summary: Tidy up your machine learning experiments
Home-page: https://github.com/AdilZouitine/Outfit
Author: Adil Zouitine
Author-email: adilzouitine@gmail.com
License: BSD-3
Platform: UNKNOWN
Classifier: License :: OSI Approved :: BSD License
Classifier: Programming Language :: Python
Classifier: Programming Language :: Python :: 3
Classifier: Programming Language :: Python :: 3.5
Classifier: Programming Language :: Python :: 3.6
Classifier: Programming Language :: Python :: 3.7
Classifier: Programming Language :: Python :: Implementation :: PyPy
Requires-Python: >=3.5.0
Requires-Dist: peewee (>=3.9.6)
Requires-Dist: pandas (>=0.24.2)
Requires-Dist: tabulate (>=0.8.3)
